geoterminal/__init__.py
geoterminal/_version.py
geoterminal/cli/__init__.py
geoterminal/cli/main.py
geoterminal/cli/parser.py
geoterminal/cli/processor.py
geoterminal/io/file.py
geoterminal/log.py
geoterminal/operators/data_operations.py
geoterminal/operators/geometry_operations.py
geoterminal/operators/h3_operations.py
geoterminal/operators/inspect_operations.py
geoterminal-0.1.4.dist-info/LICENSE
geoterminal-0.1.4.dist-info/METADATA
geoterminal-0.1.4.dist-info/WHEEL
geoterminal-0.1.4.dist-info/entry_points.txt
geoterminal-0.1.4.dist-info/RECORD
