Metadata-Version: 2.3
Name: geoterminal
Version: 0.1.4
Summary: geoterminal is a command-line tool designed to simplify common GIS tasks that you may encounter in your daily work.
License: MIT
Author: Jerónimo Luza
Author-email: jero.luza@gmail.com
Requires-Python: >=3.10
Classifier: License :: OSI Approved :: MIT License
Classifier: Programming Language :: Python :: 3
Classifier: Programming Language :: Python :: 3.10
Classifier: Programming Language :: Python :: 3.11
Classifier: Programming Language :: Python :: 3.12
Classifier: Programming Language :: Python :: 3.13
Provides-Extra: dev
Provides-Extra: docs
Requires-Dist: black (>=21.0) ; extra == "dev"
Requires-Dist: flake8 (>=3.8) ; extra == "dev"
Requires-Dist: geopandas (>=0.9.0)
Requires-Dist: h3 (>=4.1.2)
Requires-Dist: loguru (>=0.7.0)
Requires-Dist: mkdocs (>=1.6.1) ; extra == "docs"
Requires-Dist: mkdocs-material (>=9.6.11) ; extra == "docs"
Requires-Dist: pandas (>=1.2.0)
Requires-Dist: pyarrow (>=6.0.0)
Requires-Dist: pytest (>=6.0) ; extra == "dev"
Requires-Dist: shapely (>=1.7.0)
Project-URL: Homepage, https://github.com/jeronimoluza/geoterminal
Project-URL: Repository, https://github.com/jeronimoluza/geoterminal
